Vinted_api_scraper/__init__.py
Vinted_api_scraper/requester.py
Vinted_api_scraper/settings.py
Vinted_api_scraper/vinted.py
Vinted_api_scraper/items/__init__.py
Vinted_api_scraper/items/item.py
Vinted_api_scraper/items/items.py
Vinted_api_scraper-0.5.0.dist-info/LICENSE
Vinted_api_scraper-0.5.0.dist-info/METADATA
Vinted_api_scraper-0.5.0.dist-info/WHEEL
Vinted_api_scraper-0.5.0.dist-info/top_level.txt
Vinted_api_scraper-0.5.0.dist-info/RECORD
