Metadata-Version: 2.1
Name: Vinted-api-scraper
Version: 0.5.0
Summary: Vinted API wrapper for python
Home-page: https://github.com/simonbeguin/Vinted_api_scraper
Author: Simon BEGUIN
Author-email: simon.beguin7@gmail.com
License: UNKNOWN
Keywords: python,Vinted api,Vinted API wrapper,python vinted
Platform: UNKNOWN
Classifier: Programming Language :: Python :: 3
Classifier: License :: OSI Approved :: MIT License
Classifier: Operating System :: OS Independent
Classifier: Intended Audience :: Education
Requires-Python: >=3.6
Requires-Dist: requests
